libjpathgen.libs/libgeos-d898651c.so.3.12.1
libjpathgen.libs/libgcc_s-a04fdf82.so.1
libjpathgen.libs/libjpathgen-87802caa.so
libjpathgen.libs/libstdc++-a9383cce.so.6.0.28
libjpathgen.libs/libcubpackpp-661ad38e.so.0.1.0
libjpathgen-0.3.3.dist-info/RECORD
libjpathgen-0.3.3.dist-info/entry_points.txt
libjpathgen-0.3.3.dist-info/METADATA
libjpathgen-0.3.3.dist-info/WHEEL
libjpathgen-0.3.3.dist-info/licenses/LICENSE.txt
libjpathgen/_version.py
libjpathgen/__init__.py
libjpathgen/_core.cpython-312-x86_64-linux-musl.so
