Metadata-Version: 2.1
Name: libjpathgen
Version: 0.3.3
Summary: A C++ library to speed up jpathgen computations
Classifier: Development Status :: 3 - Alpha
Classifier: Natural Language :: English
Classifier: Operating System :: Unix
Classifier: Topic :: Scientific/Engineering
Classifier: Topic :: Software Development :: Libraries :: Python Modules
Classifier: Topic :: Utilities
Classifier: Programming Language :: C++
Project-URL: Homepage, https://github.com/iwishiwasaneagle/libjpathgen
Project-URL: Bug tracker, https://github.com/iwishiwasaneagle/libjpathgen/issues
Project-URL: Discussions, https://github.comiwishiwasaneagle/libjpathgen/discussions
Requires-Python: >=3.10
Provides-Extra: test
Requires-Dist: pytest; extra == "test"
Requires-Dist: numpy; extra == "test"
License-File: LICENSE.txt
